LICENSE.txt
MANIFEST.in
README.rst
setup.py
testy/__init__.py
testy/aliases.py
testy/assertions.py
testy/utils.py
testy.egg-info/PKG-INFO
testy.egg-info/SOURCES.txt
testy.egg-info/dependency_links.txt
testy.egg-info/top_level.txt